apps/__init__.py
apps/image_classification/__init__.py
apps/image_classification/run_inference.py
apps/image_classification/run_testing.py
apps/image_classification/run_training.py
apps/image_segmentation/__init__.py
apps/image_segmentation/run_inference.py
apps/image_segmentation/run_testing.py
apps/image_segmentation/run_training.py
apps/neural_style_transfer/__init__.py
apps/neural_style_transfer/run_neural_style_transfer.py
pytorchDL/__init__.py
pytorchDL/dataset_iterator.py
pytorchDL/layers.py
pytorchDL/loggers.py
pytorchDL/metrics.py
pytorchDL/trainer_base.py
pytorchDL/networks/__init__.py
pytorchDL/networks/dcgan.py
pytorchDL/networks/resnet.py
pytorchDL/networks/unet.py
pytorchDL/networks/vgg.py
pytorchDL/tasks/__init__.py
pytorchDL/tasks/image_classification/__init__.py
pytorchDL/tasks/image_classification/data.py
pytorchDL/tasks/image_classification/evaluator.py
pytorchDL/tasks/image_classification/predictor.py
pytorchDL/tasks/image_classification/trainer.py
pytorchDL/tasks/image_segmentation/__init__.py
pytorchDL/tasks/image_segmentation/data.py
pytorchDL/tasks/image_segmentation/evaluator.py
pytorchDL/tasks/image_segmentation/predictor.py
pytorchDL/tasks/image_segmentation/trainer.py
pytorchDL/tasks/neural_style_transfer/__init__.py
pytorchDL/tasks/neural_style_transfer/feature_extractor.py
pytorchDL/tasks/neural_style_transfer/predictor.py
pytorchDL/utils/__init__.py
pytorchDL/utils/color.py
pytorchDL/utils/imgproc.py
pytorchDL/utils/io.py
pytorchDL/utils/misc.py
pytorchDL-0.6.6.dist-info/LICENSE
pytorchDL-0.6.6.dist-info/METADATA
pytorchDL-0.6.6.dist-info/WHEEL
pytorchDL-0.6.6.dist-info/entry_points.txt
pytorchDL-0.6.6.dist-info/top_level.txt
pytorchDL-0.6.6.dist-info/RECORD
