Metadata-Version: 2.1
Name: pytorchDL
Version: 0.6.6
Summary: Package containing network definitions and utilities for pytorch deep learning framework
Home-page: https://github.com/Milogav/PytorchDL
Author: Milogav
License: UNKNOWN
Platform: UNKNOWN
Requires-Python: >=3.6
Requires-Dist: torch (>=1.5.0)
Requires-Dist: torchvision (>=0.6.0)
Requires-Dist: tqdm (>=4.46.1)
Requires-Dist: tensorboard (>=2.2.1)
Requires-Dist: opencv-contrib-python (>=4.1.2.30)
Requires-Dist: numpy (>=1.18.5)
Requires-Dist: seaborn (>=0.10.1)
Requires-Dist: Pillow (>=7.1.2)
